smack_gsheets/Google_Sheet.py
smack_gsheets/__init__.py
smack_gsheets-0.0.2.dist-info/METADATA
smack_gsheets-0.0.2.dist-info/WHEEL
smack_gsheets-0.0.2.dist-info/top_level.txt
smack_gsheets-0.0.2.dist-info/RECORD
