Metadata-Version: 2.1
Name: smack-gsheets
Version: 0.0.2
Summary: Google_Sheets API Wrapper Class
Home-page: UNKNOWN
Author: Mathew Mammen Jacob
Author-email: <mathew.mammenjacob@gmail.com>
License: UNKNOWN
Keywords: python,first package
Platform: UNKNOWN
Classifier: Development Status :: 3 - Alpha
Classifier: Intended Audience :: Education
Classifier: Programming Language :: Python :: 2
Classifier: Programming Language :: Python :: 3
Classifier: Operating System :: MacOS :: MacOS X
Classifier: Operating System :: Microsoft :: Windows
Requires-Dist: gspread
Requires-Dist: gspread-dataframe
